{
	// Place your snippets for shellscript here. Each snippet is defined under a snippet name and has a prefix, body and 
	// description. The prefix is what is used to trigger the snippet and the body will be expanded and inserted. Possible variables are:
	// $1, $2 for tab stops, $0 for the final cursor position, and ${1:label}, ${2:another} for placeholders. Placeholders with the 
	// same ids are connected.
	// Example:
	// "Print to console": {
	// 	"prefix": "log",
	// 	"body": [
	// 		"console.log('$1');",
	// 		"$2"
	// 	],
	// 	"description": "Log output to console"
	// }
	"add a shebang": {
		"prefix": "bash",
		"body": [
			"#!/bin/bash"
		],
		"description": "Add shebang to script"
	},
	"color black": {
		"prefix": "black",
		"body": [
			"\\033[30m"
		],
		"description": "Add color black"
	},
	"color Red": {
		"prefix": "red",
		"body": [
			"\\033[31m"
		],
		"description": "Add color Red"
	},
	"color Green": {
		"prefix": "green",
		"body": [
			"\\033[32m"
		],
		"description": "Add color Green"
	},
	"color brown": {
		"prefix": "brown",
		"body": [
			"\\033[33m"
		],
		"description": "Add color brown"
	},
	"color blue": {
		"prefix": "blue",
		"body": [
			"\\033[34m"
		],
		"description": "Add color blue"
	},
	"color purple": {
		"prefix": "purple",
		"body": [
			"\\033[35m"
		],
		"description": "Add color purple"
	},
	"color Cyan": {
		"prefix": "cyan",
		"body": [
			"\\033[36m"
		],
		"description": "Add color cyan"
	},
	"color grey": {
		"prefix": "grey",
		"body": [
			"\\033[37m"
		],
		"description": "Add color grey"
	},
}